brokerclient/ETrade.py
brokerclient/__init__.py
brokerclient-0.1.2.dist-info/LICENSE.txt
brokerclient-0.1.2.dist-info/METADATA
brokerclient-0.1.2.dist-info/WHEEL
brokerclient-0.1.2.dist-info/top_level.txt
brokerclient-0.1.2.dist-info/RECORD
