Metadata-Version: 2.1
Name: brokerclient
Version: 0.1.2
Summary: Connection with brokers
Home-page: https://github.com/genarionogueira
Author: Genario Nogueira
Author-email: genarionogueira2@gmail.com
License: MIT
Platform: UNKNOWN
Classifier: Programming Language :: Python :: 3
Requires-Dist: certifi (==2020.4.5.1)
Requires-Dist: chardet (==3.0.4)
Requires-Dist: idna (==2.9)
Requires-Dist: numpy (==1.18.4)
Requires-Dist: pandas (==1.0.3)
Requires-Dist: python-dateutil (==2.8.1)
Requires-Dist: pytz (==2020.1)
Requires-Dist: rauth (==0.7.3)
Requires-Dist: requests (==2.23.0)
Requires-Dist: six (==1.15.0)
Requires-Dist: urllib3 (==1.25.9)
